<INSTANCE dmrole="" dmtype="desc:EpochPositionCorrelations">
   <!-- Class holder for the correlation coefficients between the \texttt{EpochPosition} components." -->
   <ATTRIBUTE dmrole="desc:EpochPositionCorrelations.longitudeParallax" dmtype="ivoa:real" unit="" ref="@@@@@" value=""/>
   <ATTRIBUTE dmrole="desc:EpochPositionCorrelations.latitudeParallax" dmtype="ivoa:real" unit="" ref="@@@@@" value=""/>
   <ATTRIBUTE dmrole="desc:EpochPositionCorrelations.pmLongitudeParallax" dmtype="ivoa:real" unit="" ref="@@@@@" value=""/>
   <ATTRIBUTE dmrole="desc:EpochPositionCorrelations.pmLatitudeParallax" dmtype="ivoa:real" unit="" ref="@@@@@" value=""/>
   <ATTRIBUTE dmrole="desc:EpochPositionCorrelations.longitudeLatitude" dmtype="ivoa:real" unit="" ref="@@@@@" value=""/>
   <ATTRIBUTE dmrole="desc:EpochPositionCorrelations.pmLongitudePmLatitude" dmtype="ivoa:real" unit="" ref="@@@@@" value=""/>
   <ATTRIBUTE dmrole="desc:EpochPositionCorrelations.latitudePmLatitude" dmtype="ivoa:real" unit="" ref="@@@@@" value=""/>
   <ATTRIBUTE dmrole="desc:EpochPositionCorrelations.latitudePmLongitude" dmtype="ivoa:real" unit="" ref="@@@@@" value=""/>
   <ATTRIBUTE dmrole="desc:EpochPositionCorrelations.longitudePmLatitude" dmtype="ivoa:real" unit="" ref="@@@@@" value=""/>
   <ATTRIBUTE dmrole="desc:EpochPositionCorrelations.longitudePmLongitude" dmtype="ivoa:real" unit="" ref="@@@@@" value=""/>
   <ATTRIBUTE dmrole="desc:EpochPositionCorrelations.isCovariance" dmtype="ivoa:boolean" unit="" ref="@@@@@" value=""/>
</INSTANCE>
