<INSTANCE dmrole="" dmtype="desc:dataorigin.DataOrigin">
   <!-- Class representing the origin of the data following the DCP note" -->
   <ATTRIBUTE dmrole="desc:dataorigin.DataOrigin.citation" dmtype="ivoa:string" ref="@@@@@" value=""/>
   <ATTRIBUTE dmrole="desc:dataorigin.DataOrigin.reference_url" dmtype="ivoa:string" ref="@@@@@" value=""/>
   <ATTRIBUTE dmrole="desc:dataorigin.DataOrigin.resource_version" dmtype="ivoa:string" ref="@@@@@" value=""/>
   <ATTRIBUTE dmrole="desc:dataorigin.DataOrigin.creator" dmtype="ivoa:string" ref="@@@@@" value=""/>
   <ATTRIBUTE dmrole="desc:dataorigin.DataOrigin.cites" dmtype="ivoa:string" ref="@@@@@" value=""/>
   <ATTRIBUTE dmrole="desc:dataorigin.DataOrigin.is_derived_from" dmtype="ivoa:string" ref="@@@@@" value=""/>
   <ATTRIBUTE dmrole="desc:dataorigin.DataOrigin.original_date" dmtype="ivoa:datetime" unit="" ref="@@@@@" value=""/>
   <INSTANCE dmrole="desc:dataorigin.DataOrigin.query" dmtype="mango:dataorigin.QueryOrigin"/>
   <INSTANCE dmrole="desc:dataorigin.DataOrigin.rights" dmtype="mango:dataorigin.License"/>
   <INSTANCE dmrole="desc:dataorigin.DataOrigin.article" dmtype="mango:dataorigin.Article"/>
</INSTANCE>
